{
  "name": "Cancellations",
  "base": "PersistedModel",
  "options": {
    "idInjection": true ,
    "postgresql": {
      "schema": "main",
      "table": "cancellations"
    },
    "relations": {
      "cancellationsBookingIdFkeyrel": {
        "model": "Booking",
        "type": "belongsTo",
        "foreignKey": "booking_id"
      },
      "cancellationsUserIdFkeyrel": {
        "model": "Users",
        "type": "belongsTo",
        "foreignKey": "user_id"
      }
    }
  },
  "properties": {
    "id": {
      "type": "Number",
      "length": null,
      "precision": null,
      "scale": 0,
      "id": true,
      "generated": true,
      "postgresql": {
        "columnName": "id",
        "dataType": "bigint",
        "dataLength": null,
        "dataPrecision": null,
        "dataScale": 0,
        "nullable": "NO"
      }
    },
    "reason": {
      "type": "String",
      "required": true,
      "length": null,
      "precision": null,
      "scale": null,
      "postgresql": {
        "columnName": "reason",
        "dataType": "text",
        "dataLength": null,
        "dataPrecision": null,
        "dataScale": null,
        "nullable": "NO"
      }
    },
    "booking_id": {
      "type": "Number",
      "required": true,
      "length": null,
      "precision": null,
      "scale": 0,
      "postgresql": {
        "columnName": "booking_id",
        "dataType": "bigint",
        "dataLength": null,
        "dataPrecision": null,
        "dataScale": 0,
        "nullable": "NO"
      }
    },
    "user_id": {
      "type": "Number",
      "required": true,
      "length": null,
      "precision": null,
      "scale": 0,
      "postgresql": {
        "columnName": "user_id",
        "dataType": "bigint",
        "dataLength": null,
        "dataPrecision": null,
        "dataScale": 0,
        "nullable": "NO"
      }
    },
    "created_at": {
      "type": "Date",
      "default": "$now",
      "required": true,
      "length": null,
      "precision": null,
      "scale": null,
      "postgresql": {
        "columnName": "created_at",
        "dataType": "timestamp without time zone",
        "dataLength": null,
        "dataPrecision": null,
        "dataScale": null,
        "nullable": "NO"
      }
    },
    "updated_at": {
      "type": "Date",
      "required": false,
      "length": null,
      "precision": null,
      "scale": null,
      "postgresql": {
        "columnName": "updated_at",
        "dataType": "timestamp without time zone",
        "dataLength": null,
        "dataPrecision": null,
        "dataScale": null,
        "nullable": "YES"
      }
    }
  }
}
